cobolt/__init__.py
cobolt/enums.py
cobolt/exceptions.py
cobolt-0.1.0.dist-info/LICENSE
cobolt-0.1.0.dist-info/METADATA
cobolt-0.1.0.dist-info/WHEEL
cobolt-0.1.0.dist-info/top_level.txt
cobolt-0.1.0.dist-info/RECORD
